{
  "0": {
    "original": "A young bank executive related this personal experience about work capacity.",
    "b1": "",
    "cn": "",
    "ai_notes": "",
    "remarks": "",
    "play_count": 0
  },
  "1": {
    "original": "One of the other executives in our bank left us with very short notice.",
    "b1": "",
    "cn": "",
    "ai_notes": "",
    "remarks": "",
    "play_count": 0
  },
  "2": {
    "original": "This put our department on the spot.",
    "b1": "",
    "cn": "",
    "ai_notes": "",
    "remarks": "",
    "play_count": 0
  },
  "3": {
    "original": "The fellow leaving had filled an important job, and his work couldn't be postponed or left undone.",
    "b1": "",
    "cn": "",
    "ai_notes": "",
    "remarks": "",
    "play_count": 0
  },
  "4": {
    "original": "The day after he left, the vice president in charge of my department called me in.",
    "b1": "",
    "cn": "",
    "ai_notes": "",
    "remarks": "",
    "play_count": 0
  },
  "5": {
    "original": "He explained to me that he had already talked individually to the two others in my group,",
    "b1": "",
    "cn": "",
    "ai_notes": "",
    "remarks": "",
    "play_count": 0
  },
  "6": {
    "original": "asking them if they could divide the work of the man who had just left until a replacement could be found.",
    "b1": "",
    "cn": "",
    "ai_notes": "",
    "remarks": "",
    "play_count": 0
  },
  "7": {
    "original": "Neither of them flatly refused, said the vice president, but each stated that he is up to his neck now with his own pressing work.",
    "b1": "",
    "cn": "",
    "ai_notes": "",
    "remarks": "",
    "play_count": 0
  },
  "8": {
    "original": "I'm wondering if you could handle some of the overload temporarily?",
    "b1": "",
    "cn": "",
    "ai_notes": "",
    "remarks": "",
    "play_count": 0
  },
  "9": {
    "original": "Throughout my working career, I've learned that it never pays to turn down what looks like an opportunity.",
    "b1": "",
    "cn": "",
    "ai_notes": "",
    "remarks": "",
    "play_count": 0
  },
  "10": {
    "original": "So I agreed and promised to do my very best to handle all the vacated job as well as keep up with my own work.",
    "b1": "",
    "cn": "",
    "ai_notes": "",
    "remarks": "",
    "play_count": 0
  },
  "11": {
    "original": "The Vice President was pleased at this.",
    "b1": "",
    "cn": "",
    "ai_notes": "",
    "remarks": "",
    "play_count": 0
  },
  "12": {
    "original": "I walked out of his office knowing I had taken on a big job.",
    "b1": "",
    "cn": "",
    "ai_notes": "",
    "remarks": "",
    "play_count": 0
  },
  "13": {
    "original": "I was just as busy as the two others in my department who had wiggled out of this extra duty.",
    "b1": "",
    "cn": "",
    "ai_notes": "",
    "remarks": "",
    "play_count": 0
  },
  "14": {
    "original": "But I was determined to find a way to handle both jobs.",
    "b1": "",
    "cn": "",
    "ai_notes": "",
    "remarks": "",
    "play_count": 0
  },
  "15": {
    "original": "I finished up my work that afternoon, and when the offices were closed,",
    "b1": "",
    "cn": "",
    "ai_notes": "",
    "remarks": "",
    "play_count": 0
  },
  "16": {
    "original": "I sat down to figure out how I could increase my personal efficiency.",
    "b1": "",
    "cn": "",
    "ai_notes": "",
    "remarks": "",
    "play_count": 0
  },
  "17": {
    "original": "I got a pencil and started writing down every idea I could think of.",
    "b1": "",
    "cn": "",
    "ai_notes": "",
    "remarks": "",
    "play_count": 0
  },
  "18": {
    "original": "And you know, I came up with some good ones, like working out an arrangement with my secretary to channel all routine telephone calls to me during a certain hour each day,",
    "b1": "",
    "cn": "",
    "ai_notes": "",
    "remarks": "",
    "play_count": 0
  },
  "19": {
    "original": "placing all outgoing calls during a certain hour, cutting my usual conference periods from fifteen minutes to ten,",
    "b1": "",
    "cn": "",
    "ai_notes": "",
    "remarks": "",
    "play_count": 0
  },
  "20": {
    "original": "giving all my dictation at one time each day.",
    "b1": "",
    "cn": "",
    "ai_notes": "",
    "remarks": "",
    "play_count": 0
  },
  "21": {
    "original": "I also discovered my secretary could and was eager to take over a number of little time-consuming details for me.",
    "b1": "",
    "cn": "",
    "ai_notes": "",
    "remarks": "",
    "play_count": 0
  },
  "22": {
    "original": "I had been handling my present job for over two years, and frankly,",
    "b1": "",
    "cn": "",
    "ai_notes": "",
    "remarks": "",
    "play_count": 0
  },
  "23": {
    "original": "I was amazed to discover how much inefficiency I had let creep in.",
    "b1": "",
    "cn": "",
    "ai_notes": "",
    "remarks": "",
    "play_count": 0
  },
  "24": {
    "original": "Within a week's time, I was dictating twice as many letters, handling fifty percent more phone calls,",
    "b1": "",
    "cn": "",
    "ai_notes": "",
    "remarks": "",
    "play_count": 0
  },
  "25": {
    "original": "attending half again as many meetings, all with no strain.",
    "b1": "",
    "cn": "",
    "ai_notes": "",
    "remarks": "",
    "play_count": 0
  },
  "26": {
    "original": "A couple more weeks passed.",
    "b1": "",
    "cn": "",
    "ai_notes": "",
    "remarks": "",
    "play_count": 0
  },
  "27": {
    "original": "The vice president called me in.",
    "b1": "",
    "cn": "",
    "ai_notes": "",
    "remarks": "",
    "play_count": 0
  },
  "28": {
    "original": "He complimented me on doing a fine job.",
    "b1": "",
    "cn": "",
    "ai_notes": "",
    "remarks": "",
    "play_count": 0
  },
  "29": {
    "original": "He went on to say that he had looked over a number of people from both inside and outside the bank,",
    "b1": "",
    "cn": "",
    "ai_notes": "",
    "remarks": "",
    "play_count": 0
  },
  "30": {
    "original": "but he had not yet found the right man.",
    "b1": "",
    "cn": "",
    "ai_notes": "",
    "remarks": "",
    "play_count": 0
  },
  "31": {
    "original": "Then he confessed that he had already cleared with the bank's executive committee,",
    "b1": "",
    "cn": "",
    "ai_notes": "",
    "remarks": "",
    "play_count": 0
  },
  "32": {
    "original": "and they had authorized him to combine the two jobs, put them both in my charge,",
    "b1": "",
    "cn": "",
    "ai_notes": "",
    "remarks": "",
    "play_count": 0
  },
  "33": {
    "original": "and give me a substantial increase in salary.",
    "b1": "",
    "cn": "",
    "ai_notes": "",
    "remarks": "",
    "play_count": 0
  },
  "34": {
    "original": "I prove to myself that how much I can do depends on how much I think I can do.",
    "b1": "",
    "cn": "",
    "ai_notes": "",
    "remarks": "",
    "play_count": 0
  },
  "35": {
    "original": "Capacity is indeed a state of mind.",
    "b1": "",
    "cn": "",
    "ai_notes": "",
    "remarks": "",
    "play_count": 0
  }
}